[
 {
  "tarikh": "۱۳۹۸/۸/۲۵",
  "date": "2019-11-16",
  "count": 436,
  "volume": 21786938,
  "value": 18817157625,
  "open": 860,
  "high": 946,
  "low": 855,
  "close": 875,
  "final": 864
 },
 {
  "tarikh": "۱۳۹۸/۶/۶",
  "date": "2019-08-28",
  "count": 281,
  "volume": 7962284,
  "value": 6208519099,
  "open": 786,
  "high": 795,
  "low": 750,
  "close": 795,
  "final": 780
 },
 {
  "tarikh": "۱۳۹۸/۶/۵",
  "date": "2019-08-27",
  "count": 123,
  "volume": 4739145,
  "value": 3426401835,
  "open": 723,
  "high": 723,
  "low": 723,
  "close": 723,
  "final": 723
 },
 {
  "tarikh": "۱۳۹۸/۶/۴",
  "date": "2019-08-26",
  "count": 73,
  "volume": 1560921,
  "value": 1027421846,
  "open": 604,
  "high": 662,
  "low": 604,
  "close": 662,
  "final": 658
 },
 {
  "tarikh": "۱۳۹۸/۶/۳",
  "date": "2019-08-25",
  "count": 131,
  "volume": 1756003,
  "value": 1056316372,
  "open": 647,
  "high": 650,
  "low": 581,
  "close": 631,
  "final": 602
 },
 {
  "tarikh": "۱۳۹۸/۶/۲",
  "date": "2019-08-24",
  "count": 123,
  "volume": 1617412,
  "value": 1043209820,
  "open": 645,
  "high": 660,
  "low": 623,
  "close": 650,
  "final": 645
 },
 {
  "tarikh": "۱۳۹۸/۵/۳۰",
  "date": "2019-08-21",
  "count": 122,
  "volume": 2433226,
  "value": 1599234994,
  "open": 650,
  "high": 670,
  "low": 630,
  "close": 643,
  "final": 657
 },
 {
  "tarikh": "۱۳۹۸/۵/۲۸",
  "date": "2019-08-19",
  "count": 133,
  "volume": 1275761,
  "value": 801896573,
  "open": 581,
  "high": 656,
  "low": 581,
  "close": 650,
  "final": 629
 },
 {
  "tarikh": "۱۳۹۸/۵/۲۷",
  "date": "2019-08-18",
  "count": 107,
  "volume": 1672177,
  "value": 1021602625,
  "open": 660,
  "high": 660,
  "low": 600,
  "close": 600,
  "final": 611
 },
 {
  "tarikh": "۱۳۹۸/۵/۲۶",
  "date": "2019-08-17",
  "count": 139,
  "volume": 1578358,
  "value": 1027442886,
  "open": 659,
  "high": 669,
  "low": 614,
  "close": 658,
  "final": 651
 },
 {
  "tarikh": "۱۳۹۸/۵/۲۳",
  "date": "2019-08-14",
  "count": 213,
  "volume": 3123023,
  "value": 2052838457,
  "open": 640,
  "high": 680,
  "low": 629,
  "close": 660,
  "final": 657
 },
 {
  "tarikh": "۱۳۹۸/۵/۲۲",
  "date": "2019-08-13",
  "count": 181,
  "volume": 3141835,
  "value": 1980703696,
  "open": 580,
  "high": 638,
  "low": 574,
  "close": 638,
  "final": 630
 },
 {
  "tarikh": "۱۳۹۸/۵/۲۰",
  "date": "2019-08-11",
  "count": 40,
  "volume": 234058,
  "value": 135709572,
  "open": 589,
  "high": 619,
  "low": 548,
  "close": 578,
  "final": 580
 },
 {
  "tarikh": "۱۳۹۸/۵/۱۹",
  "date": "2019-08-10",
  "count": 42,
  "volume": 199150,
  "value": 121015611,
  "open": 605,
  "high": 619,
  "low": 583,
  "close": 602,
  "final": 608
 },
 {
  "tarikh": "۱۳۹۸/۵/۱۶",
  "date": "2019-08-07",
  "count": 128,
  "volume": 1524757,
  "value": 908708124,
  "open": 600,
  "high": 610,
  "low": 574,
  "close": 601,
  "final": 596
 },
 {
  "tarikh": "۱۳۹۸/۵/۱۵",
  "date": "2019-08-06",
  "count": 144,
  "volume": 1207469,
  "value": 768640150,
  "open": 609,
  "high": 646,
  "low": 609,
  "close": 630,
  "final": 637
 },
 {
  "tarikh": "۱۳۹۸/۵/۱۴",
  "date": "2019-08-05",
  "count": 170,
  "volume": 1325825,
  "value": 780031785,
  "open": 550,
  "high": 607,
  "low": 540,
  "close": 607,
  "final": 588
 },
 {
  "tarikh": "۱۳۹۸/۵/۱۳",
  "date": "2019-08-04",
  "count": 47,
  "volume": 252418,
  "value": 139359780,
  "open": 535,
  "high": 577,
  "low": 530,
  "close": 567,
  "final": 552
 },
 {
  "tarikh": "۱۳۹۸/۵/۱۲",
  "date": "2019-08-03",
  "count": 81,
  "volume": 713086,
  "value": 402058173,
  "open": 510,
  "high": 576,
  "low": 510,
  "close": 561,
  "final": 564
 },
 {
  "tarikh": "۱۳۹۸/۵/۹",
  "date": "2019-07-31",
  "count": 64,
  "volume": 357775,
  "value": 187789293,
  "open": 510,
  "high": 539,
  "low": 510,
  "close": 520,
  "final": 525
 },
 {
  "tarikh": "۱۳۹۸/۵/۸",
  "date": "2019-07-30",
  "count": 87,
  "volume": 591019,
  "value": 308209653,
  "open": 540,
  "high": 540,
  "low": 500,
  "close": 512,
  "final": 521
 },
 {
  "tarikh": "۱۳۹۸/۵/۷",
  "date": "2019-07-29",
  "count": 117,
  "volume": 1939702,
  "value": 969232556,
  "open": 538,
  "high": 540,
  "low": 489,
  "close": 519,
  "final": 500
 },
 {
  "tarikh": "۱۳۹۸/۵/۶",
  "date": "2019-07-28",
  "count": 27,
  "volume": 94175,
  "value": 51169536,
  "open": 552,
  "high": 565,
  "low": 534,
  "close": 538,
  "final": 543
 },
 {
  "tarikh": "۱۳۹۸/۵/۵",
  "date": "2019-07-27",
  "count": 48,
  "volume": 449955,
  "value": 244364405,
  "open": 561,
  "high": 575,
  "low": 538,
  "close": 545,
  "final": 543
 },
 {
  "tarikh": "۱۳۹۸/۵/۲",
  "date": "2019-07-24",
  "count": 54,
  "volume": 650183,
  "value": 364440118,
  "open": 550,
  "high": 585,
  "low": 530,
  "close": 543,
  "final": 561
 },
 {
  "tarikh": "۱۳۹۸/۵/۱",
  "date": "2019-07-23",
  "count": 25,
  "volume": 70885,
  "value": 38680737,
  "open": 546,
  "high": 576,
  "low": 531,
  "close": 545,
  "final": 546
 },
 {
  "tarikh": "۱۳۹۸/۴/۳۱",
  "date": "2019-07-22",
  "count": 28,
  "volume": 61097,
  "value": 34081693,
  "open": 585,
  "high": 585,
  "low": 546,
  "close": 553,
  "final": 558
 },
 {
  "tarikh": "۱۳۹۸/۴/۳۰",
  "date": "2019-07-21",
  "count": 131,
  "volume": 1224100,
  "value": 716251999,
  "open": 523,
  "high": 592,
  "low": 523,
  "close": 587,
  "final": 585
 },
 {
  "tarikh": "۱۳۹۸/۴/۲۹",
  "date": "2019-07-20",
  "count": 30,
  "volume": 158673,
  "value": 85600586,
  "open": 544,
  "high": 559,
  "low": 523,
  "close": 550,
  "final": 539
 },
 {
  "tarikh": "۱۳۹۸/۴/۲۶",
  "date": "2019-07-17",
  "count": 38,
  "volume": 173404,
  "value": 95763115,
  "open": 544,
  "high": 575,
  "low": 533,
  "close": 544,
  "final": 552
 },
 {
  "tarikh": "۱۳۹۸/۴/۲۵",
  "date": "2019-07-16",
  "count": 80,
  "volume": 742001,
  "value": 396649613,
  "open": 530,
  "high": 575,
  "low": 530,
  "close": 532,
  "final": 535
 },
 {
  "tarikh": "۱۳۹۸/۴/۲۴",
  "date": "2019-07-15",
  "count": 47,
  "volume": 462629,
  "value": 262093568,
  "open": 558,
  "high": 590,
  "low": 556,
  "close": 556,
  "final": 567
 },
 {
  "tarikh": "۱۳۹۸/۴/۲۳",
  "date": "2019-07-14",
  "count": 59,
  "volume": 184167,
  "value": 108051360,
  "open": 561,
  "high": 600,
  "low": 561,
  "close": 585,
  "final": 587
 },
 {
  "tarikh": "۱۳۹۸/۴/۲۲",
  "date": "2019-07-13",
  "count": 118,
  "volume": 521323,
  "value": 292937962,
  "open": 557,
  "high": 572,
  "low": 556,
  "close": 572,
  "final": 562
 },
 {
  "tarikh": "۱۳۹۸/۴/۱۹",
  "date": "2019-07-10",
  "count": 108,
  "volume": 746760,
  "value": 426260265,
  "open": 580,
  "high": 580,
  "low": 563,
  "close": 580,
  "final": 571
 },
 {
  "tarikh": "۱۳۹۸/۴/۱۸",
  "date": "2019-07-09",
  "count": 163,
  "volume": 1021278,
  "value": 595818013,
  "open": 596,
  "high": 599,
  "low": 580,
  "close": 589,
  "final": 583
 },
 {
  "tarikh": "۱۳۹۸/۴/۱۷",
  "date": "2019-07-08",
  "count": 161,
  "volume": 1202945,
  "value": 731150932,
  "open": 623,
  "high": 624,
  "low": 600,
  "close": 608,
  "final": 608
 },
 {
  "tarikh": "۱۳۹۸/۴/۱۶",
  "date": "2019-07-07",
  "count": 237,
  "volume": 1503072,
  "value": 926469324,
  "open": 640,
  "high": 640,
  "low": 578,
  "close": 611,
  "final": 616
 },
 {
  "tarikh": "۱۳۹۸/۴/۱۵",
  "date": "2019-07-06",
  "count": 532,
  "volume": 5064942,
  "value": 3185784256,
  "open": 631,
  "high": 631,
  "low": 605,
  "close": 631,
  "final": 629
 },
 {
  "tarikh": "۱۳۹۸/۴/۱۲",
  "date": "2019-07-03",
  "count": 83,
  "volume": 369781,
  "value": 212254294,
  "open": 574,
  "high": 574,
  "low": 574,
  "close": 574,
  "final": 574
 },
 {
  "tarikh": "۱۳۹۸/۴/۱۱",
  "date": "2019-07-02",
  "count": 81,
  "volume": 343869,
  "value": 179499618,
  "open": 522,
  "high": 522,
  "low": 522,
  "close": 522,
  "final": 522
 },
 {
  "tarikh": "۱۳۹۸/۴/۱۰",
  "date": "2019-07-01",
  "count": 25,
  "volume": 67415,
  "value": 32046784,
  "open": 440,
  "high": 484,
  "low": 440,
  "close": 484,
  "final": 475
 },
 {
  "tarikh": "۱۳۹۷/۱۲/۱۲",
  "date": "2019-03-03",
  "count": 988,
  "volume": 46693502,
  "value": 19275195858,
  "open": 500,
  "high": 500,
  "low": 412,
  "close": 414,
  "final": 413
 },
 {
  "tarikh": "۱۳۹۷/۱۲/۱۱",
  "date": "2019-03-02",
  "count": 4,
  "volume": 95205,
  "value": 43318275,
  "open": 455,
  "high": 455,
  "low": 455,
  "close": 455,
  "final": 455
 },
 {
  "tarikh": "۱۳۹۷/۱۲/۸",
  "date": "2019-02-27",
  "count": 4,
  "volume": 56868,
  "value": 28728432,
  "open": 544,
  "high": 544,
  "low": 500,
  "close": 500,
  "final": 505
 },
 {
  "tarikh": "۱۳۹۷/۱۲/۷",
  "date": "2019-02-26",
  "count": 3,
  "volume": 3083,
  "value": 1677152,
  "open": 544,
  "high": 544,
  "low": 544,
  "close": 544,
  "final": 544
 },
 {
  "tarikh": "۱۳۹۷/۱۲/۶",
  "date": "2019-02-25",
  "count": 7,
  "volume": 28015,
  "value": 15240160,
  "open": 544,
  "high": 544,
  "low": 544,
  "close": 544,
  "final": 544
 },
 {
  "tarikh": "۱۳۹۷/۱۲/۵",
  "date": "2019-02-24",
  "count": 18,
  "volume": 655200,
  "value": 324324000,
  "open": 495,
  "high": 495,
  "low": 495,
  "close": 495,
  "final": 495
 },
 {
  "tarikh": "۱۳۹۷/۱۲/۴",
  "date": "2019-02-23",
  "count": 44,
  "volume": 2004132,
  "value": 902045340,
  "open": 450,
  "high": 495,
  "low": 450,
  "close": 495,
  "final": 450
 },
 {
  "tarikh": "۱۳۹۷/۹/۲۴",
  "date": "2018-12-15",
  "count": 629,
  "volume": 7193701,
  "value": 2766026419,
  "open": 374,
  "high": 395,
  "low": 370,
  "close": 370,
  "final": 385
 },
 {
  "tarikh": "۱۳۹۷/۹/۲۱",
  "date": "2018-12-12",
  "count": 393,
  "volume": 4840535,
  "value": 1800966975,
  "open": 353,
  "high": 400,
  "low": 350,
  "close": 380,
  "final": 372
 },
 {
  "tarikh": "۱۳۹۷/۹/۲۰",
  "date": "2018-12-11",
  "count": 269,
  "volume": 3112076,
  "value": 1136887325,
  "open": 384,
  "high": 390,
  "low": 351,
  "close": 361,
  "final": 365
 },
 {
  "tarikh": "۱۳۹۷/۹/۱۹",
  "date": "2018-12-10",
  "count": 229,
  "volume": 2553965,
  "value": 994922599,
  "open": 400,
  "high": 400,
  "low": 385,
  "close": 385,
  "final": 390
 },
 {
  "tarikh": "۱۳۹۷/۹/۱۸",
  "date": "2018-12-09",
  "count": 119,
  "volume": 1612580,
  "value": 635816967,
  "open": 392,
  "high": 402,
  "low": 390,
  "close": 392,
  "final": 394
 },
 {
  "tarikh": "۱۳۹۷/۹/۱۷",
  "date": "2018-12-08",
  "count": 177,
  "volume": 3184750,
  "value": 1283406369,
  "open": 391,
  "high": 417,
  "low": 380,
  "close": 406,
  "final": 403
 },
 {
  "tarikh": "۱۳۹۷/۹/۱۴",
  "date": "2018-12-05",
  "count": 143,
  "volume": 1861567,
  "value": 751899228,
  "open": 407,
  "high": 418,
  "low": 396,
  "close": 408,
  "final": 404
 },
 {
  "tarikh": "۱۳۹۷/۹/۱۳",
  "date": "2018-12-04",
  "count": 111,
  "volume": 1211630,
  "value": 497441066,
  "open": 419,
  "high": 419,
  "low": 401,
  "close": 408,
  "final": 411
 },
 {
  "tarikh": "۱۳۹۷/۹/۱۲",
  "date": "2018-12-03",
  "count": 135,
  "volume": 1710520,
  "value": 704755003,
  "open": 400,
  "high": 419,
  "low": 396,
  "close": 412,
  "final": 412
 },
 {
  "tarikh": "۱۳۹۷/۹/۱۱",
  "date": "2018-12-02",
  "count": 124,
  "volume": 898042,
  "value": 357798234,
  "open": 408,
  "high": 411,
  "low": 390,
  "close": 395,
  "final": 398
 },
 {
  "tarikh": "۱۳۹۷/۹/۱۰",
  "date": "2018-12-01",
  "count": 203,
  "volume": 3373621,
  "value": 1346619892,
  "open": 423,
  "high": 429,
  "low": 390,
  "close": 407,
  "final": 399
 },
 {
  "tarikh": "۱۳۹۷/۹/۷",
  "date": "2018-11-28",
  "count": 134,
  "volume": 1631424,
  "value": 706049531,
  "open": 445,
  "high": 452,
  "low": 429,
  "close": 429,
  "final": 433
 },
 {
  "tarikh": "۱۳۹۷/۹/۶",
  "date": "2018-11-27",
  "count": 147,
  "volume": 1682790,
  "value": 763713734,
  "open": 453,
  "high": 469,
  "low": 447,
  "close": 448,
  "final": 454
 },
 {
  "tarikh": "۱۳۹۷/۹/۵",
  "date": "2018-11-26",
  "count": 125,
  "volume": 1293125,
  "value": 595193464,
  "open": 459,
  "high": 474,
  "low": 453,
  "close": 468,
  "final": 460
 },
 {
  "tarikh": "۱۳۹۷/۹/۳",
  "date": "2018-11-24",
  "count": 170,
  "volume": 1763207,
  "value": 806598055,
  "open": 464,
  "high": 475,
  "low": 451,
  "close": 460,
  "final": 457
 },
 {
  "tarikh": "۱۳۹۷/۸/۳۰",
  "date": "2018-11-21",
  "count": 179,
  "volume": 2096863,
  "value": 978970993,
  "open": 494,
  "high": 494,
  "low": 451,
  "close": 474,
  "final": 467
 },
 {
  "tarikh": "۱۳۹۷/۸/۲۹",
  "date": "2018-11-20",
  "count": 147,
  "volume": 1628610,
  "value": 789913487,
  "open": 457,
  "high": 500,
  "low": 457,
  "close": 486,
  "final": 485
 },
 {
  "tarikh": "۱۳۹۷/۸/۲۸",
  "date": "2018-11-19",
  "count": 102,
  "volume": 800257,
  "value": 390674338,
  "open": 489,
  "high": 495,
  "low": 477,
  "close": 477,
  "final": 488
 },
 {
  "tarikh": "۱۳۹۷/۸/۲۷",
  "date": "2018-11-18",
  "count": 208,
  "volume": 2393949,
  "value": 1168959714,
  "open": 500,
  "high": 511,
  "low": 464,
  "close": 490,
  "final": 488
 },
 {
  "tarikh": "۱۳۹۷/۸/۲۶",
  "date": "2018-11-17",
  "count": 213,
  "volume": 1808419,
  "value": 915657854,
  "open": 510,
  "high": 524,
  "low": 495,
  "close": 500,
  "final": 506
 },
 {
  "tarikh": "۱۳۹۷/۸/۲۳",
  "date": "2018-11-14",
  "count": 98,
  "volume": 493441,
  "value": 251065516,
  "open": 503,
  "high": 524,
  "low": 503,
  "close": 509,
  "final": 509
 },
 {
  "tarikh": "۱۳۹۷/۸/۲۲",
  "date": "2018-11-13",
  "count": 201,
  "volume": 1369841,
  "value": 708077859,
  "open": 525,
  "high": 533,
  "low": 501,
  "close": 511,
  "final": 517
 },
 {
  "tarikh": "۱۳۹۷/۸/۲۱",
  "date": "2018-11-12",
  "count": 170,
  "volume": 1580169,
  "value": 832985090,
  "open": 547,
  "high": 547,
  "low": 520,
  "close": 525,
  "final": 527
 },
 {
  "tarikh": "۱۳۹۷/۸/۲۰",
  "date": "2018-11-11",
  "count": 157,
  "volume": 1475397,
  "value": 771300465,
  "open": 559,
  "high": 559,
  "low": 506,
  "close": 527,
  "final": 523
 },
 {
  "tarikh": "۱۳۹۷/۸/۱۹",
  "date": "2018-11-10",
  "count": 177,
  "volume": 1244040,
  "value": 675109584,
  "open": 518,
  "high": 558,
  "low": 518,
  "close": 535,
  "final": 543
 },
 {
  "tarikh": "۱۳۹۷/۸/۱۵",
  "date": "2018-11-06",
  "count": 214,
  "volume": 1067655,
  "value": 560371808,
  "open": 508,
  "high": 537,
  "low": 508,
  "close": 536,
  "final": 525
 },
 {
  "tarikh": "۱۳۹۷/۸/۱۴",
  "date": "2018-11-05",
  "count": 157,
  "volume": 956472,
  "value": 498316181,
  "open": 514,
  "high": 535,
  "low": 514,
  "close": 519,
  "final": 521
 },
 {
  "tarikh": "۱۳۹۷/۸/۱۳",
  "date": "2018-11-04",
  "count": 117,
  "volume": 460862,
  "value": 239525238,
  "open": 513,
  "high": 549,
  "low": 507,
  "close": 514,
  "final": 520
 },
 {
  "tarikh": "۱۳۹۷/۸/۱۲",
  "date": "2018-11-03",
  "count": 118,
  "volume": 604422,
  "value": 325784386,
  "open": 587,
  "high": 587,
  "low": 524,
  "close": 534,
  "final": 539
 },
 {
  "tarikh": "۱۳۹۷/۸/۹",
  "date": "2018-10-31",
  "count": 203,
  "volume": 1933732,
  "value": 1112952538,
  "open": 571,
  "high": 592,
  "low": 555,
  "close": 575,
  "final": 576
 },
 {
  "tarikh": "۱۳۹۷/۸/۷",
  "date": "2018-10-29",
  "count": 202,
  "volume": 2008517,
  "value": 1186326240,
  "open": 610,
  "high": 613,
  "low": 559,
  "close": 570,
  "final": 591
 },
 {
  "tarikh": "۱۳۹۷/۸/۶",
  "date": "2018-10-28",
  "count": 371,
  "volume": 3389108,
  "value": 1952973914,
  "open": 540,
  "high": 592,
  "low": 540,
  "close": 592,
  "final": 576
 },
 {
  "tarikh": "۱۳۹۷/۸/۵",
  "date": "2018-10-27",
  "count": 221,
  "volume": 1347818,
  "value": 726296994,
  "open": 515,
  "high": 559,
  "low": 515,
  "close": 549,
  "final": 539
 },
 {
  "tarikh": "۱۳۹۷/۸/۲",
  "date": "2018-10-24",
  "count": 253,
  "volume": 2417802,
  "value": 1374030960,
  "open": 569,
  "high": 600,
  "low": 567,
  "close": 567,
  "final": 568
 },
 {
  "tarikh": "۱۳۹۷/۸/۱",
  "date": "2018-10-23",
  "count": 416,
  "volume": 4390719,
  "value": 2764344135,
  "open": 667,
  "high": 694,
  "low": 614,
  "close": 623,
  "final": 630
 },
 {
  "tarikh": "۱۳۹۷/۷/۳۰",
  "date": "2018-10-22",
  "count": 595,
  "volume": 4855282,
  "value": 3312301150,
  "open": 750,
  "high": 750,
  "low": 652,
  "close": 680,
  "final": 682
 },
 {
  "tarikh": "۱۳۹۷/۷/۲۹",
  "date": "2018-10-21",
  "count": 1740,
  "volume": 6958855,
  "value": 5031458082,
  "open": 740,
  "high": 767,
  "low": 657,
  "close": 714,
  "final": 723
 },
 {
  "tarikh": "۱۳۹۷/۷/۲۸",
  "date": "2018-10-20",
  "count": 809,
  "volume": 3098961,
  "value": 2217743786,
  "open": 668,
  "high": 734,
  "low": 668,
  "close": 734,
  "final": 716
 }
]