[
 {
  "tarikh": "۱۳۹۹/۳/۱۱",
  "date": "2020-05-31",
  "count": 1,
  "volume": 10000,
  "value": 964280000,
  "open": 96428,
  "high": 96428,
  "low": 96428,
  "close": 96428,
  "final": 101440
 },
 {
  "tarikh": "۱۳۹۹/۲/۶",
  "date": "2020-04-25",
  "count": 2,
  "volume": 15000,
  "value": 1214810000,
  "open": 82962,
  "high": 82962,
  "low": 80000,
  "close": 80000,
  "final": 82925
 },
 {
  "tarikh": "۱۳۹۹/۲/۱",
  "date": "2020-04-20",
  "count": 1,
  "volume": 30000,
  "value": 2309760000,
  "open": 76992,
  "high": 76992,
  "low": 76992,
  "close": 76992,
  "final": 80892
 },
 {
  "tarikh": "۱۳۹۸/۵/۶",
  "date": "2019-07-28",
  "count": 1,
  "volume": 1000,
  "value": 8123000,
  "open": 8123,
  "high": 8123,
  "low": 8123,
  "close": 8123,
  "final": 7951
 },
 {
  "tarikh": "۱۳۹۸/۳/۸",
  "date": "2019-05-29",
  "count": 18,
  "volume": 500000,
  "value": 5600000000,
  "open": 11200,
  "high": 11200,
  "low": 11200,
  "close": 11200,
  "final": 11298
 },
 {
  "tarikh": "۱۳۹۸/۳/۷",
  "date": "2019-05-28",
  "count": 35,
  "volume": 1999000,
  "value": 21923933000,
  "open": 11789,
  "high": 11789,
  "low": 10667,
  "close": 10667,
  "final": 10967
 },
 {
  "tarikh": "۱۳۹۷/۱۲/۲۶",
  "date": "2019-03-17",
  "count": 15,
  "volume": 1249999,
  "value": 6749994600,
  "open": 5400,
  "high": 5400,
  "low": 5400,
  "close": 5400,
  "final": 5400
 },
 {
  "tarikh": "۱۳۹۷/۱۱/۲۷",
  "date": "2019-02-16",
  "count": 5,
  "volume": 497000,
  "value": 2549113000,
  "open": 5129,
  "high": 5129,
  "low": 5129,
  "close": 5129,
  "final": 5129
 },
 {
  "tarikh": "۱۳۹۷/۶/۱۹",
  "date": "2018-09-10",
  "count": 4,
  "volume": 200000,
  "value": 966000000,
  "open": 4830,
  "high": 4830,
  "low": 4830,
  "close": 4830,
  "final": 4995
 },
 {
  "tarikh": "۱۳۹۷/۶/۱۸",
  "date": "2018-09-09",
  "count": 6,
  "volume": 200000,
  "value": 960000000,
  "open": 4800,
  "high": 4800,
  "low": 4800,
  "close": 4800,
  "final": 4950
 },
 {
  "tarikh": "۱۳۹۷/۶/۴",
  "date": "2018-08-26",
  "count": 3,
  "volume": 99998,
  "value": 441991160,
  "open": 4420,
  "high": 4420,
  "low": 4420,
  "close": 4420,
  "final": 4610
 },
 {
  "tarikh": "۱۳۹۷/۶/۳",
  "date": "2018-08-25",
  "count": 77,
  "volume": 7499997,
  "value": 32999986800,
  "open": 4400,
  "high": 4400,
  "low": 4400,
  "close": 4400,
  "final": 4400
 },
 {
  "tarikh": "۱۳۹۷/۵/۲۴",
  "date": "2018-08-15",
  "count": 145,
  "volume": 7500000,
  "value": 29481000000,
  "open": 4100,
  "high": 3933,
  "low": 3900,
  "close": 3900,
  "final": 3931
 },
 {
  "tarikh": "۱۳۹۷/۴/۳۰",
  "date": "2018-07-21",
  "count": 18,
  "volume": 1747000,
  "value": 8787410000,
  "open": 5030,
  "high": 5030,
  "low": 5030,
  "close": 5030,
  "final": 5030
 },
 {
  "tarikh": "۱۳۹۷/۴/۱۲",
  "date": "2018-07-03",
  "count": 8,
  "volume": 494997,
  "value": 2598734250,
  "open": 5250,
  "high": 5250,
  "low": 5250,
  "close": 5250,
  "final": 5231
 },
 {
  "tarikh": "۱۳۹۷/۴/۱۰",
  "date": "2018-07-01",
  "count": 32,
  "volume": 3124999,
  "value": 15624995000,
  "open": 5000,
  "high": 5000,
  "low": 5000,
  "close": 5000,
  "final": 5000
 },
 {
  "tarikh": "۱۳۹۷/۴/۲",
  "date": "2018-06-23",
  "count": 375,
  "volume": 7363635,
  "value": 29749085400,
  "open": 4040,
  "high": 4040,
  "low": 4040,
  "close": 4040,
  "final": 4040
 },
 {
  "tarikh": "۱۳۹۷/۳/۲۸",
  "date": "2018-06-18",
  "count": 11,
  "volume": 1049997,
  "value": 3994188588,
  "open": 3804,
  "high": 3804,
  "low": 3804,
  "close": 3804,
  "final": 3804
 },
 {
  "tarikh": "۱۳۹۷/۳/۱۲",
  "date": "2018-06-02",
  "count": 2,
  "volume": 104165,
  "value": 335098805,
  "open": 3217,
  "high": 3217,
  "low": 3217,
  "close": 3217,
  "final": 3217
 },
 {
  "tarikh": "۱۳۹۷/۱/۲۷",
  "date": "2018-04-16",
  "count": 64,
  "volume": 6249998,
  "value": 20312493500,
  "open": 3250,
  "high": 3250,
  "low": 3250,
  "close": 3250,
  "final": 3250
 },
 {
  "tarikh": "۱۳۹۷/۱/۲۶",
  "date": "2018-04-15",
  "count": 137,
  "volume": 13524998,
  "value": 43956243500,
  "open": 3250,
  "high": 3250,
  "low": 3250,
  "close": 3250,
  "final": 3250
 },
 {
  "tarikh": "۱۳۹۷/۱/۲۲",
  "date": "2018-04-11",
  "count": 11,
  "volume": 1100000,
  "value": 3572800000,
  "open": 3248,
  "high": 3248,
  "low": 3248,
  "close": 3248,
  "final": 3248
 },
 {
  "tarikh": "۱۳۹۷/۱/۲۱",
  "date": "2018-04-10",
  "count": 6,
  "volume": 600000,
  "value": 1951200000,
  "open": 3252,
  "high": 3252,
  "low": 3252,
  "close": 3252,
  "final": 3252
 },
 {
  "tarikh": "۱۳۹۷/۱/۲۰",
  "date": "2018-04-09",
  "count": 4,
  "volume": 400000,
  "value": 1298400000,
  "open": 3246,
  "high": 3246,
  "low": 3246,
  "close": 3246,
  "final": 3195
 },
 {
  "tarikh": "۱۳۹۷/۱/۷",
  "date": "2018-03-27",
  "count": 1,
  "volume": 20832,
  "value": 61225248,
  "open": 2939,
  "high": 2939,
  "low": 2939,
  "close": 2939,
  "final": 3088
 },
 {
  "tarikh": "۱۳۹۶/۳/۱۶",
  "date": "2017-06-06",
  "count": 1,
  "volume": 100000,
  "value": 409000000,
  "open": 4090,
  "high": 4090,
  "low": 4090,
  "close": 4090,
  "final": 4090
 },
 {
  "tarikh": "۱۳۹۶/۱/۲۷",
  "date": "2017-04-16",
  "count": 20,
  "volume": 2000000,
  "value": 9100000000,
  "open": 4550,
  "high": 4550,
  "low": 4550,
  "close": 4550,
  "final": 4550
 },
 {
  "tarikh": "۱۳۹۶/۱/۲۱",
  "date": "2017-04-10",
  "count": 9,
  "volume": 833332,
  "value": 3791660600,
  "open": 4550,
  "high": 4550,
  "low": 4550,
  "close": 4550,
  "final": 4550
 },
 {
  "tarikh": "۱۳۹۵/۱۲/۱",
  "date": "2017-02-19",
  "count": 5,
  "volume": 500000,
  "value": 2450000000,
  "open": 4900,
  "high": 4900,
  "low": 4900,
  "close": 4900,
  "final": 4900
 },
 {
  "tarikh": "۱۳۹۵/۱۱/۲۷",
  "date": "2017-02-15",
  "count": 32,
  "volume": 3124998,
  "value": 15315615198,
  "open": 4901,
  "high": 4901,
  "low": 4901,
  "close": 4901,
  "final": 4901
 },
 {
  "tarikh": "۱۳۹۵/۱۱/۱۸",
  "date": "2017-02-06",
  "count": 1,
  "volume": 60605,
  "value": 307267350,
  "open": 5070,
  "high": 5070,
  "low": 5070,
  "close": 5070,
  "final": 5070
 }
]