[
 {
  "tarikh": "۱۳۹۷/۳/۲۹",
  "date": "2018-06-19",
  "count": 7,
  "volume": 206888,
  "value": 932792704,
  "open": 4300,
  "high": 4583,
  "low": 4300,
  "close": 4583,
  "final": 4509
 },
 {
  "tarikh": "۱۳۹۷/۳/۲۸",
  "date": "2018-06-18",
  "count": 4,
  "volume": 129000,
  "value": 537500000,
  "open": 4000,
  "high": 4300,
  "low": 4000,
  "close": 4300,
  "final": 4167
 },
 {
  "tarikh": "۱۳۹۷/۳/۲۷",
  "date": "2018-06-17",
  "count": 6,
  "volume": 230000,
  "value": 966000000,
  "open": 4200,
  "high": 4200,
  "low": 4200,
  "close": 4200,
  "final": 4200
 },
 {
  "tarikh": "۱۳۹۷/۳/۲۳",
  "date": "2018-06-13",
  "count": 6,
  "volume": 110000,
  "value": 452500000,
  "open": 4110,
  "high": 4150,
  "low": 4110,
  "close": 4150,
  "final": 4114
 },
 {
  "tarikh": "۱۳۹۶/۹/۲۹",
  "date": "2017-12-20",
  "count": 1,
  "volume": 957,
  "value": 3828000,
  "open": 4000,
  "high": 4000,
  "low": 4000,
  "close": 4000,
  "final": 4000
 },
 {
  "tarikh": "۱۳۹۶/۹/۲۸",
  "date": "2017-12-19",
  "count": 4,
  "volume": 5586,
  "value": 22344000,
  "open": 4000,
  "high": 4000,
  "low": 4000,
  "close": 4000,
  "final": 4000
 },
 {
  "tarikh": "۱۳۹۶/۹/۲۷",
  "date": "2017-12-18",
  "count": 9,
  "volume": 25631,
  "value": 97578120,
  "open": 3800,
  "high": 4080,
  "low": 3800,
  "close": 4080,
  "final": 3807
 },
 {
  "tarikh": "۱۳۹۶/۹/۲۶",
  "date": "2017-12-17",
  "count": 4,
  "volume": 10000,
  "value": 37100000,
  "open": 3710,
  "high": 3710,
  "low": 3710,
  "close": 3710,
  "final": 3710
 },
 {
  "tarikh": "۱۳۹۶/۹/۲۱",
  "date": "2017-12-12",
  "count": 3,
  "volume": 87585,
  "value": 359098500,
  "open": 4100,
  "high": 4100,
  "low": 4100,
  "close": 4100,
  "final": 4100
 },
 {
  "tarikh": "۱۳۹۶/۹/۲۰",
  "date": "2017-12-11",
  "count": 10,
  "volume": 10320,
  "value": 43880640,
  "open": 4252,
  "high": 4252,
  "low": 4252,
  "close": 4252,
  "final": 4252
 },
 {
  "tarikh": "۱۳۹۶/۹/۱۹",
  "date": "2017-12-10",
  "count": 1,
  "volume": 10,
  "value": 47240,
  "open": 4724,
  "high": 4724,
  "low": 4724,
  "close": 4724,
  "final": 4724
 },
 {
  "tarikh": "۱۳۹۶/۹/۵",
  "date": "2017-11-26",
  "count": 3,
  "volume": 3129,
  "value": 16420494,
  "open": 5596,
  "high": 5553,
  "low": 5199,
  "close": 5553,
  "final": 5248
 },
 {
  "tarikh": "۱۳۹۶/۹/۱",
  "date": "2017-11-22",
  "count": 21,
  "volume": 40675,
  "value": 208215325,
  "open": 5119,
  "high": 5119,
  "low": 5119,
  "close": 5119,
  "final": 5119
 },
 {
  "tarikh": "۱۳۹۶/۸/۳۰",
  "date": "2017-11-21",
  "count": 6,
  "volume": 10833,
  "value": 50416782,
  "open": 4654,
  "high": 4654,
  "low": 4654,
  "close": 4654,
  "final": 4654
 },
 {
  "tarikh": "۱۳۹۶/۸/۲۹",
  "date": "2017-11-20",
  "count": 3,
  "volume": 896,
  "value": 3790976,
  "open": 4231,
  "high": 4231,
  "low": 4231,
  "close": 4231,
  "final": 4231
 },
 {
  "tarikh": "۱۳۹۶/۸/۲۷",
  "date": "2017-11-18",
  "count": 4,
  "volume": 342,
  "value": 1315674,
  "open": 3847,
  "high": 3847,
  "low": 3847,
  "close": 3847,
  "final": 3847
 },
 {
  "tarikh": "۱۳۹۶/۸/۲۴",
  "date": "2017-11-15",
  "count": 6,
  "volume": 10379,
  "value": 36307720,
  "open": 3498,
  "high": 3500,
  "low": 3498,
  "close": 3498,
  "final": 3498
 }
]