[
 {
  "tarikh": "۱۳۹۵/۳/۲۵",
  "date": "2016-06-14",
  "count": 793,
  "volume": 24599870,
  "value": 66519341330,
  "open": 2811,
  "high": 3000,
  "low": 2702,
  "close": 2711,
  "final": 2704
 },
 {
  "tarikh": "۱۳۹۵/۱/۱۱",
  "date": "2016-03-30",
  "count": 899,
  "volume": 11234996,
  "value": 46411701852,
  "open": 3860,
  "high": 4246,
  "low": 3860,
  "close": 4246,
  "final": 4131
 },
 {
  "tarikh": "۱۳۹۴/۱۲/۱۶",
  "date": "2016-03-06",
  "count": 401,
  "volume": 2498363,
  "value": 12311562904,
  "open": 4946,
  "high": 4946,
  "low": 4830,
  "close": 4946,
  "final": 4928
 },
 {
  "tarikh": "۱۳۹۴/۱۲/۱۵",
  "date": "2016-03-05",
  "count": 67,
  "volume": 498794,
  "value": 2243076618,
  "open": 4497,
  "high": 4497,
  "low": 4497,
  "close": 4497,
  "final": 4497
 },
 {
  "tarikh": "۱۳۹۴/۱۲/۱۲",
  "date": "2016-03-02",
  "count": 445,
  "volume": 3399881,
  "value": 13903578223,
  "open": 4084,
  "high": 4094,
  "low": 3731,
  "close": 4094,
  "final": 4089
 },
 {
  "tarikh": "۱۳۹۴/۱۲/۱۱",
  "date": "2016-03-01",
  "count": 354,
  "volume": 3052174,
  "value": 11360280510,
  "open": 3680,
  "high": 3734,
  "low": 3620,
  "close": 3734,
  "final": 3722
 },
 {
  "tarikh": "۱۳۹۴/۱۲/۱۰",
  "date": "2016-02-29",
  "count": 226,
  "volume": 2225163,
  "value": 7554878809,
  "open": 3406,
  "high": 3406,
  "low": 3255,
  "close": 3406,
  "final": 3395
 },
 {
  "tarikh": "۱۳۹۴/۱۲/۹",
  "date": "2016-02-28",
  "count": 278,
  "volume": 3426470,
  "value": 10612173777,
  "open": 3098,
  "high": 3098,
  "low": 2901,
  "close": 3098,
  "final": 3097
 },
 {
  "tarikh": "۱۳۹۴/۱۲/۸",
  "date": "2016-02-27",
  "count": 10,
  "volume": 39923,
  "value": 112463091,
  "open": 2817,
  "high": 2817,
  "low": 2817,
  "close": 2817,
  "final": 2817
 },
 {
  "tarikh": "۱۳۹۴/۱۲/۵",
  "date": "2016-02-24",
  "count": 416,
  "volume": 4028948,
  "value": 10318699999,
  "open": 2413,
  "high": 2890,
  "low": 2413,
  "close": 2700,
  "final": 2561
 },
 {
  "tarikh": "۱۳۹۴/۱۲/۴",
  "date": "2016-02-23",
  "count": 98,
  "volume": 889157,
  "value": 2383462026,
  "open": 2685,
  "high": 2689,
  "low": 2675,
  "close": 2675,
  "final": 2681
 },
 {
  "tarikh": "۱۳۹۴/۱۲/۳",
  "date": "2016-02-22",
  "count": 279,
  "volume": 1986453,
  "value": 5903873009,
  "open": 2820,
  "high": 3277,
  "low": 2751,
  "close": 2871,
  "final": 2972
 },
 {
  "tarikh": "۱۳۹۴/۱۲/۲",
  "date": "2016-02-21",
  "count": 122,
  "volume": 923341,
  "value": 2818359785,
  "open": 3040,
  "high": 3459,
  "low": 3031,
  "close": 3031,
  "final": 3052
 },
 {
  "tarikh": "۱۳۹۴/۱۲/۱",
  "date": "2016-02-20",
  "count": 381,
  "volume": 3677345,
  "value": 12381051257,
  "open": 3700,
  "high": 3800,
  "low": 3239,
  "close": 3239,
  "final": 3367
 },
 {
  "tarikh": "۱۳۹۴/۱۱/۲۸",
  "date": "2016-02-17",
  "count": 567,
  "volume": 4732833,
  "value": 17027581382,
  "open": 3310,
  "high": 3709,
  "low": 3310,
  "close": 3689,
  "final": 3598
 },
 {
  "tarikh": "۱۳۹۴/۱۱/۲۷",
  "date": "2016-02-16",
  "count": 590,
  "volume": 7004826,
  "value": 24218179922,
  "open": 3445,
  "high": 3577,
  "low": 3310,
  "close": 3510,
  "final": 3457
 },
 {
  "tarikh": "۱۳۹۴/۱۱/۲۶",
  "date": "2016-02-15",
  "count": 354,
  "volume": 2705064,
  "value": 8902734910,
  "open": 3100,
  "high": 3370,
  "low": 3100,
  "close": 3289,
  "final": 3291
 },
 {
  "tarikh": "۱۳۹۴/۱۱/۲۵",
  "date": "2016-02-14",
  "count": 342,
  "volume": 1980930,
  "value": 6339949638,
  "open": 3200,
  "high": 3398,
  "low": 3050,
  "close": 3163,
  "final": 3200
 },
 {
  "tarikh": "۱۳۹۴/۱۱/۲۴",
  "date": "2016-02-13",
  "count": 340,
  "volume": 2114875,
  "value": 6755665437,
  "open": 3195,
  "high": 3290,
  "low": 2900,
  "close": 3000,
  "final": 3194
 },
 {
  "tarikh": "۱۳۹۴/۱۱/۲۱",
  "date": "2016-02-10",
  "count": 395,
  "volume": 3808537,
  "value": 11727422755,
  "open": 2652,
  "high": 3160,
  "low": 2652,
  "close": 3052,
  "final": 3079
 },
 {
  "tarikh": "۱۳۹۴/۱۱/۲۰",
  "date": "2016-02-09",
  "count": 212,
  "volume": 2613100,
  "value": 7611095870,
  "open": 2831,
  "high": 2941,
  "low": 2711,
  "close": 2887,
  "final": 2913
 },
 {
  "tarikh": "۱۳۹۴/۱۱/۱۹",
  "date": "2016-02-08",
  "count": 585,
  "volume": 5348887,
  "value": 14304172989,
  "open": 2600,
  "high": 2819,
  "low": 2500,
  "close": 2600,
  "final": 2674
 },
 {
  "tarikh": "۱۳۹۴/۱۱/۱۸",
  "date": "2016-02-07",
  "count": 588,
  "volume": 4809092,
  "value": 12430772661,
  "open": 2470,
  "high": 2661,
  "low": 2470,
  "close": 2531,
  "final": 2585
 },
 {
  "tarikh": "۱۳۹۴/۱۱/۱۷",
  "date": "2016-02-06",
  "count": 459,
  "volume": 4173462,
  "value": 10100483868,
  "open": 2251,
  "high": 2459,
  "low": 2250,
  "close": 2459,
  "final": 2420
 },
 {
  "tarikh": "۱۳۹۴/۱۱/۱۴",
  "date": "2016-02-03",
  "count": 569,
  "volume": 5464014,
  "value": 12215990962,
  "open": 2206,
  "high": 2395,
  "low": 2206,
  "close": 2206,
  "final": 2236
 },
 {
  "tarikh": "۱۳۹۴/۱۱/۱۳",
  "date": "2016-02-02",
  "count": 838,
  "volume": 7416027,
  "value": 18175191722,
  "open": 2688,
  "high": 2688,
  "low": 2381,
  "close": 2381,
  "final": 2451
 },
 {
  "tarikh": "۱۳۹۴/۱۱/۱۲",
  "date": "2016-02-01",
  "count": 851,
  "volume": 6787315,
  "value": 17949285458,
  "open": 2705,
  "high": 2887,
  "low": 2415,
  "close": 2650,
  "final": 2645
 },
 {
  "tarikh": "۱۳۹۴/۱۱/۱۱",
  "date": "2016-01-31",
  "count": 338,
  "volume": 2251187,
  "value": 5985099757,
  "open": 2500,
  "high": 2750,
  "low": 2500,
  "close": 2690,
  "final": 2659
 },
 {
  "tarikh": "۱۳۹۴/۱۱/۷",
  "date": "2016-01-27",
  "count": 540,
  "volume": 4561214,
  "value": 11220356895,
  "open": 2510,
  "high": 2513,
  "low": 2120,
  "close": 2491,
  "final": 2460
 },
 {
  "tarikh": "۱۳۹۴/۱۱/۶",
  "date": "2016-01-26",
  "count": 159,
  "volume": 2100308,
  "value": 4798423620,
  "open": 2285,
  "high": 2285,
  "low": 2280,
  "close": 2285,
  "final": 2285
 },
 {
  "tarikh": "۱۳۹۴/۱۱/۵",
  "date": "2016-01-25",
  "count": 147,
  "volume": 1278866,
  "value": 2657664673,
  "open": 2039,
  "high": 2110,
  "low": 1941,
  "close": 2110,
  "final": 2078
 },
 {
  "tarikh": "۱۳۹۴/۱۱/۴",
  "date": "2016-01-24",
  "count": 365,
  "volume": 2860826,
  "value": 5490375386,
  "open": 1828,
  "high": 1969,
  "low": 1828,
  "close": 1969,
  "final": 1919
 },
 {
  "tarikh": "۱۳۹۴/۱۱/۳",
  "date": "2016-01-23",
  "count": 529,
  "volume": 5986486,
  "value": 10718603420,
  "open": 1631,
  "high": 1852,
  "low": 1631,
  "close": 1851,
  "final": 1790
 },
 {
  "tarikh": "۱۳۹۴/۱۰/۳۰",
  "date": "2016-01-20",
  "count": 434,
  "volume": 3800556,
  "value": 6399436483,
  "open": 1650,
  "high": 1760,
  "low": 1600,
  "close": 1711,
  "final": 1684
 },
 {
  "tarikh": "۱۳۹۴/۱۰/۲۹",
  "date": "2016-01-19",
  "count": 282,
  "volume": 2947547,
  "value": 4737664768,
  "open": 1520,
  "high": 1611,
  "low": 1510,
  "close": 1611,
  "final": 1607
 },
 {
  "tarikh": "۱۳۹۴/۱۰/۲۸",
  "date": "2016-01-18",
  "count": 609,
  "volume": 5713039,
  "value": 8369664936,
  "open": 1500,
  "high": 1549,
  "low": 1330,
  "close": 1530,
  "final": 1465
 },
 {
  "tarikh": "۱۳۹۴/۱۰/۲۷",
  "date": "2016-01-17",
  "count": 780,
  "volume": 9339338,
  "value": 13412453037,
  "open": 1457,
  "high": 1457,
  "low": 1240,
  "close": 1457,
  "final": 1436
 },
 {
  "tarikh": "۱۳۹۴/۱۰/۲۶",
  "date": "2016-01-16",
  "count": 11,
  "volume": 266145,
  "value": 352642125,
  "open": 1325,
  "high": 1325,
  "low": 1325,
  "close": 1325,
  "final": 1325
 },
 {
  "tarikh": "۱۳۹۴/۱۰/۲۳",
  "date": "2016-01-13",
  "count": 150,
  "volume": 2480163,
  "value": 2987565553,
  "open": 1205,
  "high": 1205,
  "low": 1188,
  "close": 1205,
  "final": 1205
 },
 {
  "tarikh": "۱۳۹۴/۱۰/۲۲",
  "date": "2016-01-12",
  "count": 450,
  "volume": 6158071,
  "value": 6748692203,
  "open": 1098,
  "high": 1098,
  "low": 986,
  "close": 1098,
  "final": 1096
 },
 {
  "tarikh": "۱۳۹۴/۱۰/۲۱",
  "date": "2016-01-11",
  "count": 58,
  "volume": 826184,
  "value": 825328330,
  "open": 940,
  "high": 1010,
  "low": 940,
  "close": 1010,
  "final": 999
 },
 {
  "tarikh": "۱۳۹۴/۱۰/۲۰",
  "date": "2016-01-10",
  "count": 213,
  "volume": 2494262,
  "value": 2291516427,
  "open": 890,
  "high": 940,
  "low": 880,
  "close": 936,
  "final": 919
 },
 {
  "tarikh": "۱۳۹۴/۱۰/۱۹",
  "date": "2016-01-09",
  "count": 126,
  "volume": 900450,
  "value": 773154707,
  "open": 780,
  "high": 892,
  "low": 780,
  "close": 869,
  "final": 859
 },
 {
  "tarikh": "۱۳۹۴/۱۰/۱۶",
  "date": "2016-01-06",
  "count": 872,
  "volume": 8778688,
  "value": 7209573744,
  "open": 872,
  "high": 873,
  "low": 800,
  "close": 873,
  "final": 821
 },
 {
  "tarikh": "۱۳۹۴/۱۰/۱۵",
  "date": "2016-01-05",
  "count": 166,
  "volume": 1471021,
  "value": 1168686475,
  "open": 730,
  "high": 803,
  "low": 730,
  "close": 803,
  "final": 794
 },
 {
  "tarikh": "۱۳۸۴/۵/۲۳",
  "date": "2005-08-14",
  "count": 13,
  "volume": 26352,
  "value": 28699184,
  "open": 1081,
  "high": 1096,
  "low": 1080,
  "close": 1089,
  "final": 1089
 },
 {
  "tarikh": "۱۳۸۴/۵/۲۲",
  "date": "2005-08-13",
  "count": 23,
  "volume": 58512,
  "value": 58390330,
  "open": 990,
  "high": 1000,
  "low": 990,
  "close": 997,
  "final": 997
 },
 {
  "tarikh": "۱۳۸۴/۵/۱۹",
  "date": "2005-08-10",
  "count": 6,
  "volume": 7388,
  "value": 7314120,
  "open": 990,
  "high": 990,
  "low": 990,
  "close": 990,
  "final": 990
 },
 {
  "tarikh": "۱۳۸۴/۵/۱۸",
  "date": "2005-08-09",
  "count": 1,
  "volume": 481,
  "value": 440596,
  "open": 916,
  "high": 916,
  "low": 916,
  "close": 916,
  "final": 916
 },
 {
  "tarikh": "۱۳۸۴/۵/۱۶",
  "date": "2005-08-07",
  "count": 3,
  "volume": 4970,
  "value": 4927548,
  "open": 991,
  "high": 992,
  "low": 991,
  "close": 991,
  "final": 991
 },
 {
  "tarikh": "۱۳۸۴/۵/۱۵",
  "date": "2005-08-06",
  "count": 5,
  "volume": 10846,
  "value": 10805042,
  "open": 996,
  "high": 997,
  "low": 996,
  "close": 996,
  "final": 996
 },
 {
  "tarikh": "۱۳۸۴/۵/۱۲",
  "date": "2005-08-03",
  "count": 2,
  "volume": 646,
  "value": 586330,
  "open": 908,
  "high": 908,
  "low": 907,
  "close": 907,
  "final": 907
 },
 {
  "tarikh": "۱۳۸۴/۵/۱۱",
  "date": "2005-08-02",
  "count": 4,
  "volume": 9010,
  "value": 8106990,
  "open": 900,
  "high": 900,
  "low": 898,
  "close": 899,
  "final": 899
 },
 {
  "tarikh": "۱۳۸۴/۵/۱۰",
  "date": "2005-08-01",
  "count": 3,
  "volume": 10000,
  "value": 9210000,
  "open": 921,
  "high": 921,
  "low": 921,
  "close": 921,
  "final": 921
 },
 {
  "tarikh": "۱۳۸۴/۵/۹",
  "date": "2005-07-31",
  "count": 1,
  "volume": 590,
  "value": 603570,
  "open": 1023,
  "high": 1023,
  "low": 1023,
  "close": 1023,
  "final": 1023
 },
 {
  "tarikh": "۱۳۸۴/۵/۸",
  "date": "2005-07-30",
  "count": 9,
  "volume": 19860,
  "value": 19601870,
  "open": 988,
  "high": 988,
  "low": 986,
  "close": 987,
  "final": 987
 },
 {
  "tarikh": "۱۳۸۴/۵/۵",
  "date": "2005-07-27",
  "count": 17,
  "volume": 42730,
  "value": 44266854,
  "open": 1010,
  "high": 1038,
  "low": 1010,
  "close": 1035,
  "final": 1035
 },
 {
  "tarikh": "۱۳۸۴/۵/۴",
  "date": "2005-07-26",
  "count": 39,
  "volume": 72179,
  "value": 72349165,
  "open": 993,
  "high": 1037,
  "low": 993,
  "close": 1002,
  "final": 1002
 },
 {
  "tarikh": "۱۳۸۴/۵/۳",
  "date": "2005-07-25",
  "count": 1,
  "volume": 300,
  "value": 283800,
  "open": 946,
  "high": 946,
  "low": 946,
  "close": 946,
  "final": 946
 },
 {
  "tarikh": "۱۳۸۴/۵/۲",
  "date": "2005-07-24",
  "count": 3,
  "volume": 5167,
  "value": 4443620,
  "open": 860,
  "high": 860,
  "low": 860,
  "close": 860,
  "final": 860
 },
 {
  "tarikh": "۱۳۸۴/۵/۱",
  "date": "2005-07-23",
  "count": 3,
  "volume": 4675,
  "value": 3659760,
  "open": 727,
  "high": 786,
  "low": 727,
  "close": 782,
  "final": 782
 },
 {
  "tarikh": "۱۳۸۴/۴/۲۹",
  "date": "2005-07-20",
  "count": 3,
  "volume": 1379,
  "value": 986456,
  "open": 654,
  "high": 719,
  "low": 654,
  "close": 715,
  "final": 715
 },
 {
  "tarikh": "۱۳۸۴/۴/۲۸",
  "date": "2005-07-19",
  "count": 7,
  "volume": 36510,
  "value": 23905540,
  "open": 650,
  "high": 670,
  "low": 608,
  "close": 654,
  "final": 654
 },
 {
  "tarikh": "۱۳۸۴/۴/۲۷",
  "date": "2005-07-18",
  "count": 16,
  "volume": 71760,
  "value": 48070440,
  "open": 659,
  "high": 727,
  "low": 655,
  "close": 669,
  "final": 669
 },
 {
  "tarikh": "۱۳۸۴/۴/۲۶",
  "date": "2005-07-17",
  "count": 26,
  "volume": 1001077,
  "value": 721973210,
  "open": 700,
  "high": 1190,
  "low": 600,
  "close": 727,
  "final": 727
 },
 {
  "tarikh": "۱۳۸۱/۲/۲۲",
  "date": "2002-05-12",
  "count": 11,
  "volume": 40000,
  "value": 39960000,
  "open": 999,
  "high": 999,
  "low": 999,
  "close": 999,
  "final": 999
 },
 {
  "tarikh": "۱۳۸۱/۲/۱۴",
  "date": "2002-05-04",
  "count": 1,
  "volume": 7220,
  "value": 11552000,
  "open": 1600,
  "high": 1600,
  "low": 1600,
  "close": 1600,
  "final": 1600
 }
]